csp-0.14.0.data/data/CMakeLists.txt
csp-0.14.0.data/data/LICENSE
csp-0.14.0.data/data/pyproject.toml
csp-0.14.0.data/data/NOTICE
csp-0.14.0.data/data/README.md
csp-0.14.0.data/data/setup.py
csp-0.14.0.data/data/vcpkg.json
csp-0.14.0.data/data/cpp/cmake/modules/FindColor.cmake
csp-0.14.0.data/data/cpp/cmake/modules/Findlz4.cmake
csp-0.14.0.data/data/cpp/cmake/modules/FindRdKafka.cmake
csp-0.14.0.data/data/cpp/cmake/modules/FindDepsArrowAdapter.cmake
csp-0.14.0.data/data/cpp/cmake/modules/FindCSP.cmake
csp-0.14.0.data/data/cpp/cmake/modules/FindDepsKafkaAdapter.cmake
csp-0.14.0.data/data/cpp/cmake/modules/FindBrotli.cmake
csp-0.14.0.data/data/cpp/cmake/modules/FindNumpy.cmake
csp-0.14.0.data/data/cpp/cmake/modules/Findutf8proc.cmake
csp-0.14.0.data/data/cpp/cmake/modules/FindPyArrow.cmake
csp-0.14.0.data/data/cpp/cmake/modules/Findcsp_autogen.cmake
csp-0.14.0.data/data/cpp/cmake/modules/FindDepsBase.cmake
csp-0.14.0.data/data/cpp/cmake/modules/FindGRPC.cmake
csp-0.14.0.data/data/cpp/cmake/modules/FindPythonHeaders.cmake
csp-0.14.0.data/data/cpp/cmake/modules/FindDepsParquetAdapter.cmake
csp-0.14.0.data/data/cpp/tests/CMakeLists.txt
csp-0.14.0.data/data/cpp/tests/core/test_platform.cpp
csp-0.14.0.data/data/cpp/tests/core/test_srmwlockfreequeue.cpp
csp-0.14.0.data/data/cpp/tests/core/test_enum.cpp
csp-0.14.0.data/data/cpp/tests/core/CMakeLists.txt
csp-0.14.0.data/data/cpp/tests/core/test_dynamicbitset.cpp
csp-0.14.0.data/data/cpp/tests/core/test_time.cpp
csp-0.14.0.data/data/cpp/tests/core/test_tagged_pointer_union.cpp
csp-0.14.0.data/data/cpp/tests/core/test_basic_allocator.cpp
csp-0.14.0.data/data/cpp/tests/engine/CMakeLists.txt
csp-0.14.0.data/data/cpp/tests/engine/test_tick_buffer.cpp
csp-0.14.0.data/data/cpp/tests/engine/test_window_buffer.cpp
csp-0.14.0.data/data/cpp/tests/engine/test_time_series.cpp
csp-0.14.0.data/data/cpp/tests/engine/test_engine_initial.cpp
csp-0.14.0.data/data/cpp/tests/engine/test_dictionary.cpp
csp-0.14.0.dist-info/RECORD
csp-0.14.0.dist-info/LICENSE
csp-0.14.0.dist-info/WHEEL
csp-0.14.0.dist-info/NOTICE
csp-0.14.0.dist-info/top_level.txt
csp-0.14.0.dist-info/METADATA
