Metadata-Version: 2.1
Name: csp
Version: 0.14.0
Summary: csp is a high performance reactive stream processing library, written in C++ and Python
Author-email: the csp authors <CSPOpenSource@point72.com>
License: Apache License
Project-URL: Repository, https://github.com/point72/csp
Project-URL: Homepage, https://github.com/Point72/csp
Project-URL: Documentation, https://github.com/Point72/csp/wiki
Project-URL: Tracker, https://github.com/point72/csp/issues
Classifier: Development Status :: 4 - Beta
Classifier: Programming Language :: Python :: Implementation :: CPython
Classifier: Programming Language :: Python :: Implementation :: PyPy
Classifier: Programming Language :: Python :: 3
Classifier: Programming Language :: Python :: 3.10
Classifier: Programming Language :: Python :: 3.11
Classifier: Programming Language :: Python :: 3.12
Classifier: Programming Language :: Python :: 3.13
Requires-Python: >=3.10
License-File: LICENSE
License-File: NOTICE
Requires-Dist: deprecated
Requires-Dist: numpy>=1
Requires-Dist: packaging
Requires-Dist: pandas
Requires-Dist: psutil
Requires-Dist: pyarrow<23,>=15
Requires-Dist: pydantic>=2
Requires-Dist: pytz
Requires-Dist: ruamel.yaml
Requires-Dist: sqlalchemy
Requires-Dist: typing-extensions
Provides-Extra: develop
Requires-Dist: bump-my-version; extra == "develop"
Requires-Dist: build; extra == "develop"
Requires-Dist: ruamel.yaml; extra == "develop"
Requires-Dist: scikit-build; extra == "develop"
Requires-Dist: twine; extra == "develop"
Requires-Dist: wheel; extra == "develop"
Requires-Dist: codespell<2.5,>=2.4; extra == "develop"
Requires-Dist: mdformat<0.8,>=0.7.19; extra == "develop"
Requires-Dist: mdformat-tables<1.1,>=1; extra == "develop"
Requires-Dist: ruff<0.15,>=0.9; extra == "develop"
Requires-Dist: pytest; extra == "develop"
Requires-Dist: pytest-asyncio; extra == "develop"
Requires-Dist: pytest-cov; extra == "develop"
Requires-Dist: pytest-sugar; extra == "develop"
Requires-Dist: graphviz; extra == "develop"
Requires-Dist: pillow; extra == "develop"
Requires-Dist: httpx<1,>=0.20; extra == "develop"
Requires-Dist: perspective-python>=2; extra == "develop"
Requires-Dist: ipywidgets; extra == "develop"
Requires-Dist: polars; extra == "develop"
Requires-Dist: psutil; extra == "develop"
Requires-Dist: sqlalchemy; extra == "develop"
Requires-Dist: threadpoolctl; extra == "develop"
Requires-Dist: tornado; extra == "develop"
Requires-Dist: python-rapidjson; extra == "develop"
Provides-Extra: showgraph
Requires-Dist: graphviz; extra == "showgraph"
Requires-Dist: pillow; extra == "showgraph"
Provides-Extra: slack
Requires-Dist: csp-adapter-slack; extra == "slack"
Provides-Extra: symphony
Requires-Dist: csp-adapter-symphony; extra == "symphony"
Provides-Extra: test
Requires-Dist: graphviz; extra == "test"
Requires-Dist: pillow; extra == "test"
Requires-Dist: pytest; extra == "test"
Requires-Dist: pytest-asyncio; extra == "test"
Requires-Dist: pytest-cov; extra == "test"
Requires-Dist: pytest-sugar; extra == "test"
Requires-Dist: httpx<1,>=0.20; extra == "test"
Requires-Dist: perspective-python; extra == "test"
Requires-Dist: polars; extra == "test"
Requires-Dist: psutil; extra == "test"
Requires-Dist: requests; extra == "test"
Requires-Dist: slack-sdk>=3; extra == "test"
Requires-Dist: sqlalchemy; extra == "test"
Requires-Dist: threadpoolctl; extra == "test"
Requires-Dist: tornado; extra == "test"
